pycli/__init__.py
pycli/__main__.py
pycli/cli/__init__.py
pycli/cli/core.py
pycli/cli/commands/__init__.py
pycli/cli/commands/cat.py
pycli/cli/commands/grep.py
pycli/cli/commands/less.py
pycli/cli/commands/ls.py
pycli/cli/commands/mkdir.py
pycli/cli/commands/tail.py
pycli/cli/commands/wc.py
pycli/cli/utils/__init__.py
pycli/cli/utils/file.py
tests/__init__.py
tests/cli/__init__.py
tests/cli/test_core.py
tests/cli/commands/__init__.py
tests/cli/commands/test_cat.py
tests/cli/commands/test_grep.py
tests/cli/commands/test_less.py
tests/cli/commands/test_ls.py
tests/cli/commands/test_mkdir.py
tests/cli/commands/test_tail.py
tests/cli/commands/test_wc.py
pycli_learning-0.0.2.dist-info/METADATA
pycli_learning-0.0.2.dist-info/WHEEL
pycli_learning-0.0.2.dist-info/top_level.txt
pycli_learning-0.0.2.dist-info/RECORD
